LICENSE.txt
README.md
setup.py
dmp_general_utils.egg-info/PKG-INFO
dmp_general_utils.egg-info/SOURCES.txt
dmp_general_utils.egg-info/dependency_links.txt
dmp_general_utils.egg-info/top_level.txt
dmp_utils/__init__.py
dmp_utils/abstract_model.py
dmp_utils/binary_uuid.py
dmp_utils/func_date.py
dmp_utils/prepare_json_response.py